odoo10_addon_l10n_ch_pain_credit_transfer-10.0.1.0.0-py2.7-nspkg.pth
odoo10_addon_l10n_ch_pain_credit_transfer-10.0.1.0.0.dist-info/top_level.txt
odoo10_addon_l10n_ch_pain_credit_transfer-10.0.1.0.0.dist-info/WHEEL
odoo10_addon_l10n_ch_pain_credit_transfer-10.0.1.0.0.dist-info/RECORD
odoo10_addon_l10n_ch_pain_credit_transfer-10.0.1.0.0.dist-info/metadata.json
odoo10_addon_l10n_ch_pain_credit_transfer-10.0.1.0.0.dist-info/DESCRIPTION.rst
odoo10_addon_l10n_ch_pain_credit_transfer-10.0.1.0.0.dist-info/METADATA
odoo10_addon_l10n_ch_pain_credit_transfer-10.0.1.0.0.dist-info/namespace_packages.txt
odoo/addons/l10n_ch_pain_credit_transfer/__manifest__.py
odoo/addons/l10n_ch_pain_credit_transfer/__init__.py
odoo/addons/l10n_ch_pain_credit_transfer/README.rst
odoo/addons/l10n_ch_pain_credit_transfer/models/account_payment_method.py
odoo/addons/l10n_ch_pain_credit_transfer/models/__init__.py
odoo/addons/l10n_ch_pain_credit_transfer/i18n/nb_NO.po
odoo/addons/l10n_ch_pain_credit_transfer/data/pain.001.001.03.ch.02.xsd
odoo/addons/l10n_ch_pain_credit_transfer/tests/test_ch_sct.py
odoo/addons/l10n_ch_pain_credit_transfer/tests/__init__.py
