Metadata-Version: 2.0
Name: odoo10-addon-l10n-ch-pain-credit-transfer
Version: 10.0.1.0.0
Summary: Generate ISO 20022 credit transfert (SEPA and not SEPA)
Home-page: UNKNOWN
Author: Akretion,Camptocamp,Odoo Community Association (OCA)
Author-email: support@odoo-community.org
License: AGPL-3
Platform: UNKNOWN
Requires-Dist: odoo (<10.1dev,>=10.0)
Requires-Dist: odoo10-addon-account-banking-sepa-credit-transfer
Requires-Dist: odoo10-addon-l10n-ch-pain-base
Classifier: Programming Language :: Python :: 2.7
Classifier: Framework :: Odoo
Classifier: License :: OSI Approved :: GNU Affero General Public License v3
